findpyx/__init__.py
findpyx/main.py
findpyx-0.1.1.dist-info/METADATA
findpyx-0.1.1.dist-info/WHEEL
findpyx-0.1.1.dist-info/top_level.txt
findpyx-0.1.1.dist-info/RECORD
