Metadata-Version: 2.1
Name: findpyx
Version: 0.1.1
Summary: Python find files script
Home-page: https://github.com/themusharraf/findpyx
Author: Musharraf Ibragimov
Author-email: meibrohimov@gmail.com
License: MIT
Classifier: License :: OSI Approved :: MIT License
Classifier: Programming Language :: Python
Classifier: Programming Language :: Python :: 3
Classifier: Programming Language :: Python :: 3.6
Classifier: Programming Language :: Python :: Implementation :: CPython
Classifier: Programming Language :: Python :: Implementation :: PyPy
Requires-Python: >=3.9.0
